django_msgspec_field/__init__.py
django_msgspec_field/_migration_serializers.py
django_msgspec_field/conf.py
django_msgspec_field/drf.py
django_msgspec_field/fields.py
django_msgspec_field/fields.pyi
django_msgspec_field/forms.py
django_msgspec_field/forms.pyi
django_msgspec_field/py.typed
django_msgspec_field/rest_framework.pyi
django_msgspec_field/types.py
django_msgspec_field/compat/__init__.py
django_msgspec_field/compat/django.py
django_msgspec_field/compat/functools.py
django_msgspec_field/compat/typing.py
django_msgspec_field/rest_framework/__init__.py
django_msgspec_field/rest_framework/coreapi.py
django_msgspec_field/rest_framework/fields.py
django_msgspec_field/rest_framework/mixins.py
django_msgspec_field/rest_framework/openapi.py
django_msgspec_field/rest_framework/parsers.py
django_msgspec_field/rest_framework/renderers.py
django_msgspec_field-0.1.11.dist-info/METADATA
django_msgspec_field-0.1.11.dist-info/WHEEL
django_msgspec_field-0.1.11.dist-info/licenses/LICENSE
django_msgspec_field-0.1.11.dist-info/RECORD
