Metadata-Version: 2.4
Name: django-msgspec-field
Version: 0.1.11
Summary: Django JSONField with msgspec structs as a Schema. Fork of django-pydantic-field.
Project-URL: Homepage, https://github.com/quertenmont/django-msgspec-field
Project-URL: Documentation, https://github.com/quertenmont/django-msgspec-field
Project-URL: Source, https://github.com/quertenmont/django-msgspec-field
Project-URL: Changelog, https://github.com/quertenmont/django-msgspec-field/releases
Project-URL: Issues, https://github.com/quertenmont/django-msgspec-field/issues
Author-email: Loic Quertenmont <loic@quertenmont.com>
Maintainer-email: Loic Quertenmont <loic@quertenmont.com>
License-Expression: MIT
License-File: LICENSE
Keywords: django,json,msgspec,schema,struct
Classifier: Development Status :: 4 - Beta
Classifier: Framework :: Django
Classifier: Framework :: Django :: 5
Classifier: Framework :: Django :: 5.0
Classifier: Framework :: Django :: 5.1
Classifier: Framework :: Django :: 5.2
Classifier: Intended Audience :: Developers
Classifier: Programming Language :: Python
Classifier: Programming Language :: Python :: 3
Classifier: Programming Language :: Python :: 3 :: Only
Classifier: Programming Language :: Python :: 3.10
Classifier: Programming Language :: Python :: 3.11
Classifier: Programming Language :: Python :: 3.12
Classifier: Programming Language :: Python :: 3.13
Classifier: Programming Language :: Python :: 3.14
Requires-Python: >=3.10
Requires-Dist: django<6,>=3.1
Requires-Dist: msgspec>=0.18.0
Requires-Dist: typing-extensions
Provides-Extra: ci
Requires-Dist: mysqlclient>=2.1; extra == 'ci'
Requires-Dist: psycopg[binary]<4,>=3.1; extra == 'ci'
Provides-Extra: coreapi
Requires-Dist: coreapi; extra == 'coreapi'
Provides-Extra: dev
Requires-Dist: django-stubs[compatible-mypy]>=5.2; extra == 'dev'
Requires-Dist: djangorestframework-stubs[compatible-mypy]>=3.16; extra == 'dev'
Requires-Dist: djangorestframework<4,>=3.11; extra == 'dev'
Requires-Dist: mypy; extra == 'dev'
Requires-Dist: pre-commit; extra == 'dev'
Requires-Dist: pytest-cov; extra == 'dev'
Requires-Dist: pytest-django<6,>=4.5; extra == 'dev'
Requires-Dist: pytest<9,>=7.4; extra == 'dev'
Requires-Dist: ruff; extra == 'dev'
Provides-Extra: jsonform
Requires-Dist: django-jsonform<3,>=2.0; extra == 'jsonform'
Provides-Extra: openapi
Requires-Dist: inflection; extra == 'openapi'
Requires-Dist: uritemplate; extra == 'openapi'
Provides-Extra: test
Requires-Dist: coreapi; extra == 'test'
Requires-Dist: dj-database-url>=2.0; extra == 'test'
Requires-Dist: django-jsonform<3,>=2.0; extra == 'test'
Requires-Dist: djangorestframework<4,>=3; extra == 'test'
Requires-Dist: inflection; extra == 'test'
Requires-Dist: pyyaml; extra == 'test'
Requires-Dist: syrupy<5,>=3; extra == 'test'
Requires-Dist: uritemplate; extra == 'test'
